cisco_mdt/__init__.py
cisco_mdt/cli.py
cisco_mdt/mdt_grpc_server.py
cisco_mdt/proto/__init__.py
cisco_mdt/proto/mdt_dialout_pb2.py
cisco_mdt/proto/mdt_dialout_pb2_grpc.py
cisco_mdt/proto/telemetry_bis_pb2.py
cisco_mdt/proto/telemetry_bis_pb2_grpc.py
cisco_mdt-0.0.1.dist-info/LICENSE
cisco_mdt-0.0.1.dist-info/METADATA
cisco_mdt-0.0.1.dist-info/WHEEL
cisco_mdt-0.0.1.dist-info/entry_points.txt
cisco_mdt-0.0.1.dist-info/top_level.txt
cisco_mdt-0.0.1.dist-info/RECORD
